proxygrabkit/__init__.py
proxygrabkit/gimmeproxy.py
proxygrabkit/proxy.py
proxygrabkit/proxyrotator.py
proxygrabkit-0.1.5.dist-info/LICENSE
proxygrabkit-0.1.5.dist-info/METADATA
proxygrabkit-0.1.5.dist-info/WHEEL
proxygrabkit-0.1.5.dist-info/top_level.txt
proxygrabkit-0.1.5.dist-info/RECORD
