Metadata-Version: 2.1
Name: proxygrabkit
Version: 0.1.5
Summary: A collection of utilities to get free proxies
Author-email: Jose Guerra Carmenate <joseguerracarmenate@gmail.com>
Project-URL: Homepage, https://github.com/joseguerra3000/ProxyGrabKit
Project-URL: Issues, https://github.com/joseguerra3000/ProxyGrabKit/issues
Classifier: Development Status :: 3 - Alpha
Classifier: Programming Language :: Python :: 3
Classifier: License :: OSI Approved :: MIT License
Classifier: Topic :: Internet :: Proxy Servers
Classifier: Topic :: Utilities
Classifier: Operating System :: OS Independent
Requires-Python: >=3.8
License-File: LICENSE
Requires-Dist: requests
Requires-Dist: dataclasses
Requires-Dist: typing
